manual/confirm_dialog_example.py
manual/demo_window.py
manual/demo_window2.py
manual/input_dialog_example.py
manual/menu_example.py
manual/menu_example2.py
manual/menu_example3.py
manual/message_dialog_example.py
manual/new_folder_dialog_example.py
manual/open_file_dialog_example.py
manual/save_file_dialog_example.py
src/guibits1_0/CursorListener.py
src/guibits1_0/__init__.py
src/guibits1_0/callback_checking1_0.py
src/guibits1_0/coloring.py
src/guibits1_0/command_listing.py
src/guibits1_0/controlling.py
src/guibits1_0/cursor_blinking.py
src/guibits1_0/cursoring.py
src/guibits1_0/dialoging.py
src/guibits1_0/file_dialoging.py
src/guibits1_0/font_size_checking.py
src/guibits1_0/font_sizing.py
src/guibits1_0/font_styling.py
src/guibits1_0/fonting.py
src/guibits1_0/keyboarding.py
src/guibits1_0/latest_listing.py
src/guibits1_0/laying_out.py
src/guibits1_0/menuing.py
src/guibits1_0/mousing.py
src/guibits1_0/painting.py
src/guibits1_0/printing.py
src/guibits1_0/qapp_creating.py
src/guibits1_0/resolving.py
src/guibits1_0/scrolling.py
src/guibits1_0/show_checking.py
src/guibits1_0/stacking.py
src/guibits1_0/type_checking2_0.py
src/guibits1_0/unicoding3_0.py
src/guibits1_0/window_bounding.py
src/guibits1_0/windowing.py
src/guibits1_0/writing.py
guibits-1.0.dist-info/METADATA
guibits-1.0.dist-info/WHEEL
guibits-1.0.dist-info/licenses/LICENCE
guibits-1.0.dist-info/RECORD
