Metadata-Version: 2.1
Name: GUIbits
Version: 1.0
Summary: A simple contract-based Graphical User Interface package
Author-email: rnb <talkguibits@gmail.com>
License-File: LICENCE
Classifier: License :: OSI Approved :: GNU General Public License (GPL)
Classifier: Operating System :: OS Independent
Classifier: Programming Language :: Python :: 3
Requires-Python: >=3.8
